lwe_python/__init__.py
lwe_python/private_key.py
lwe_python/public_key.py
lwe_python/utils.py
lwe_python/tests/__init__.py
lwe_python/tests/test_lwe.py
lwe_python-0.1.4.dist-info/METADATA
lwe_python-0.1.4.dist-info/WHEEL
lwe_python-0.1.4.dist-info/top_level.txt
lwe_python-0.1.4.dist-info/RECORD
