Metadata-Version: 2.4
Name: lwe-python
Version: 0.1.4
Summary: A Python implementation of the Learning With Errors cryptography scheme
Requires-Python: >=3.11
Requires-Dist: bitarray>=3.3.1
Requires-Dist: pytest>=8.3.5
Requires-Dist: pytest-mock>=3.14.0
